{
    "LocalizationList": [
        {
            "Key": "tap_to_continue",
            "Value": "Нажмите, чтобы продолжить"
        },
        {
            "Key": "tap_to_finish",
            "Value": "Нажмите, чтобы закончить"
        },
        {
            "Key": "tutorial_0",
            "Value": "Это старт"
        },
        {
            "Key": "tutorial_1",
            "Value": "Это финиш"
        },
        {
            "Key": "tutorial_2",
            "Value": "Вам нужно сделать путь от старта к финишу"
        },
        {
            "Key": "tutorial_completed",
            "Value": "Обучение завершено!"
        },
        {
            "Key": "level_completed",
            "Value": "Уровень пройден!"
        },
        {
            "Key": "level_not_passed",
            "Value": "Уровень не пройден!"
        },
        {
            "Key": "game_paused",
            "Value": "Игра на паузе"
        },
        {
            "Key": "steps_for_bonus",
            "Value": "\nЗавершить за {0} \nшагов"
        },
        {
            "Key": "all_levels_completed",
            "Value": "Все уровни пройдены!"
        },
        {
            "Key": "next",
            "Value": "Далее"
        },
        {
            "Key": "previous",
            "Value": "Назад"
        },
        {
            "Key": "hint_steps_text",
            "Value": "Шаг {0}/{1}"
        },
        {
            "Key": "menu_levels",
            "Value": "Уровни"
        },
        {
            "Key": "guide_1.1",
            "Value": "У вас ограниченное количество шагов"
        },
        {
            "Key": "guide_1.2",
            "Value": "Используйте эту кнопку, чтобы вернуться на один шаг назад"
        },
        {
            "Key": "guide_5",
            "Value": "<b>•</b> Нельзя передвинуть\n<b>•</b> Можно повернуть нажатием"
        },
        {
            "Key": "guide_11",
            "Value": "<b>•</b> Двигается только в двух направлениях"
        },
        {
            "Key": "new_island",
            "Value": "Новый остров!"
        },
        {
            "Key": "ad_loading_error_message",
            "Value": "<b>Не удалось загрузить рекламу.</b>\nПожалуйста, попробуйте еще раз или проверьте соединение с интернетом"
        },
        {
            "Key": "review_request",
            "Value": "<b>Мы будем рады вашим отзывам!</b>\nНам очень важно получать отзывы о нашей игре. Будем рады, если вы поделитесь своим мнением"
        },
        {
            "Key": "rate_a_game",
            "Value": "Оценить игру"
        },
        {
            "Key": "no_thanks",
            "Value": "Нет, спасибо"
        },
        {
            "Key": "loading_ad",
            "Value": "<b>Загрузка объявления. Пожалуйста, подождите.</b>\n\nЭто может занять несколько секунд, если вы смотрите рекламу впервые за сеанс."  
        }
    ]
}